README.rst
setup.cfg
setup.py
squeue/__init__.py
squeue/squeue.py
squeue/squeue_func.py
squeue.egg-info/PKG-INFO
squeue.egg-info/SOURCES.txt
squeue.egg-info/dependency_links.txt
squeue.egg-info/top_level.txt
squeue.egg-info/zip-safe