Metadata-Version: 1.1
Name: squeue
Version: 1.2
Summary: squeue: A simple SQLite Queue
Home-page: https://github.com/guilt/squeue
Author: Karthik Kumar Viswanathan
Author-email: karthikkumar@gmail.com
License: BSD
Keywords: sqlite queue job workflow
Platform: UNKNOWN
Classifier: Topic :: System :: Distributed Computing
